{
    "basic_info": {
      "description_header": "Hello",
      "description": "I am Carl Sanders, currently a student software developer at CodeCrew Collective. I was a former Airforce Veteran for 4 years stationed at Whiteman AFB. I'm currently learning the skills of computer science & software development to further my knowledge about computer programming. I am highly passionate about learning computer programming to redirect my career preference. Knowing that computers are the present and the future, I'm here to make a life changing future for myself. As well as, work to make a difference for you!",
      "section_name": {
        "about": "About me",
        "projects": "Salmon Cookies, Rock-Paper-Scissors, & chocolate-pizza",
        "skills": "HTML, CSS, JavaScript, React, bootstrap",
        "experience": "Experience"
      }
    },
    "projects": [
      {
        "title": "Salmon Cookies",
        "startDate": "2023",
        "description": "This project was a demonstration of an cookie stand shop for selling salmon cookies.",
        "images": [
          "images/portfolio/animal-shelter/p1.jpg",
          "images/portfolio/animal-shelter/p2.jpg"
        ],
        "url": "https://github.com/CEEJ987/CJ-s-Reading-Notes/tree/main/201/Class08",
        "technologies": [
          {
            "class": "CodeCrew-CodeSchool",
            "name": "Css"
          },
          {
            "class": "CodeCrew-CodeSchool",
            "name": "JavaScript"
          },
          {
            "class": "CodeCrew-CodeSchool",
            "name": "Html"
          }
        ]
      },
      {
        "title": "HornedBeast",
        "startDate": "2023",
        "description": "Personal project for study subject. I was responsible for creating an application that optimizes images with popular algorithms. ",
        "images": [
          ""
        ],
        "url": "https://github.com/CEEJ987/create-react-app/tree/main/src",
        "technologies": [
          {
            "class": "CodeCrew-CodeSchool",
            "name": "React"
          },
          {
            "class": "CodeCrew-CodeSchool",
            "name": "JavaScript"
          }
        ]
      }
      
   
    ]
  }
